postorius-1.3.13.dist-info/METADATA
postorius-1.3.13.dist-info/WHEEL
postorius-1.3.13.dist-info/licenses/COPYING
postorius/__init__.py
postorius/apps.py
postorius/auth/__init__.py
postorius/auth/decorators.py
postorius/auth/mixins.py
postorius/auth/utils.py
postorius/context_processors.py
postorius/doc/Makefile
postorius/doc/__init__.py
postorius/doc/conf.py
postorius/doc/deployment.rst
postorius/doc/development.rst
postorius/doc/index.rst
postorius/doc/news.rst
postorius/doc/settings.py
postorius/doc/setup.rst
postorius/forms/__init__.py
postorius/forms/domain_forms.py
postorius/forms/fields.py
postorius/forms/list_forms.py
postorius/forms/member_forms.py
postorius/forms/system.py
postorius/forms/user_forms.py
postorius/forms/validators.py
postorius/locale/LINGUAS
postorius/locale/af/LC_MESSAGES/django.po
postorius/locale/am/LC_MESSAGES/django.po
postorius/locale/an/LC_MESSAGES/django.po
postorius/locale/ar/LC_MESSAGES/django.po
postorius/locale/ast/LC_MESSAGES/django.po
postorius/locale/az/LC_MESSAGES/django.po
postorius/locale/be/LC_MESSAGES/django.po
postorius/locale/bem/LC_MESSAGES/django.po
postorius/locale/bg/LC_MESSAGES/django.po
postorius/locale/bn/LC_MESSAGES/django.po
postorius/locale/bo/LC_MESSAGES/django.po
postorius/locale/br/LC_MESSAGES/django.po
postorius/locale/bs/LC_MESSAGES/django.po
postorius/locale/ca/LC_MESSAGES/django.po
postorius/locale/ca@valencia/LC_MESSAGES/django.po
postorius/locale/ce/LC_MESSAGES/django.po
postorius/locale/ckb/LC_MESSAGES/django.po
postorius/locale/co/LC_MESSAGES/django.po
postorius/locale/crh/LC_MESSAGES/django.po
postorius/locale/cs/LC_MESSAGES/django.po
postorius/locale/cv/LC_MESSAGES/django.po
postorius/locale/cy/LC_MESSAGES/django.po
postorius/locale/da/LC_MESSAGES/django.po
postorius/locale/de/LC_MESSAGES/django.po
postorius/locale/el/LC_MESSAGES/django.po
postorius/locale/en_AU/LC_MESSAGES/django.po
postorius/locale/en_CA/LC_MESSAGES/django.po
postorius/locale/en_GB/LC_MESSAGES/django.po
postorius/locale/eo/LC_MESSAGES/django.po
postorius/locale/es/LC_MESSAGES/django.po
postorius/locale/et/LC_MESSAGES/django.po
postorius-1.3.13.dist-info/RECORD
