Metadata-Version: 2.1
Name: postorius
Version: 1.3.13
Summary: A web user interface for GNU Mailman
Keywords: email mailman django
Maintainer: The Mailman GSOC Coders
License: GPLv3
Classifier: Development Status :: 4 - Beta
Classifier: Framework :: Django
Classifier: License :: OSI Approved :: GNU General Public License v3 (GPLv3)
Classifier: Programming Language :: Python :: 3
Classifier: Topic :: Communications :: Email :: Mailing List Servers
Project-URL: Homepage,  https://gitlab.com/mailman/postorius
Requires-Python: >=3.9
Requires-Dist: django-mailman3>=1.3.13
Requires-Dist: django<5.1,>=4.2
Requires-Dist: mailmanclient>=3.3.3
Requires-Dist: readme_renderer[md]
Requires-Dist: pytest; extra == "test"
Requires-Dist: beautifulsoup4; extra == "test"
Requires-Dist: isort; extra == "test"
Requires-Dist: django-debug-toolbar; extra == "test"
Requires-Dist: django-requests-debug-toolbar; extra == "test"
Provides-Extra: test
